uglygrep/UglyGrep.py
uglygrep/__init__.py
uglygrep-0.1.0.dist-info/METADATA
uglygrep-0.1.0.dist-info/WHEEL
uglygrep-0.1.0.dist-info/entry_points.txt
uglygrep-0.1.0.dist-info/top_level.txt
uglygrep-0.1.0.dist-info/RECORD
