Metadata-Version: 2.1
Name: uglygrep
Version: 0.1.0
Summary: UglyGrep is a desktop application that enables you to perform text searches within multiple files in a directory. Built using Python and PyQt6, it provides an easy-to-use graphical interface for entering search patterns and locating matches across text files with a specified extension.
Home-page: https://github.com/scottpeterman/UglyGrep
Author: Scott Peterman
Author-email: scottpeterman@gmail.com
License: GPL
Classifier: Programming Language :: Python :: 3.9
Classifier: License :: OSI Approved :: GNU General Public License v3 (GPLv3)
Classifier: Operating System :: OS Independent
Requires-Python: >=3.8
Requires-Dist: keyring ==24.2.0
Requires-Dist: Pygments ==2.16.1
Requires-Dist: PyQt6 >=6.5.1
